Menus-0.2.0.dist-info/DESCRIPTION.rst
Menus-0.2.0.dist-info/METADATA
Menus-0.2.0.dist-info/RECORD
Menus-0.2.0.dist-info/WHEEL
Menus-0.2.0.dist-info/metadata.json
Menus-0.2.0.dist-info/top_level.txt
Menus-0.2.0.dist-info/zip-safe
menus/__init__.py
menus/_version.py
menus/engine.py
menus/example.py
menus/exceptions.py
menus/menu.py
menus/utils.py
site/__init__.py
